noveldl/__init__.py
noveldl/noveldl.py
noveldl/modules/__init__.py
noveldl/modules/sources/__init__.py
noveldl/modules/sources/base.py
noveldl/modules/sources/gebiqu.py
noveldl/modules/sources/xbiquge.py
noveldl/modules/sources/zw81.py
noveldl/modules/utils/__init__.py
noveldl/modules/utils/downloader.py
noveldl/modules/utils/misc.py
noveldl/modules/utils/ua.py
pynoveldl-0.1.1.dist-info/LICENSE
pynoveldl-0.1.1.dist-info/METADATA
pynoveldl-0.1.1.dist-info/WHEEL
pynoveldl-0.1.1.dist-info/entry_points.txt
pynoveldl-0.1.1.dist-info/top_level.txt
pynoveldl-0.1.1.dist-info/zip-safe
pynoveldl-0.1.1.dist-info/RECORD
