Metadata-Version: 2.1
Name: pynoveldl
Version: 0.1.1
Summary: NovelDL: Search and download novels from some specific websites
Home-page: https://github.com/CharlesPikachu/noveldl
Author: Charles
Author-email: charlesblwx@gmail.com
License: Apache License 2.0
Platform: UNKNOWN
Classifier: License :: OSI Approved :: Apache Software License
Classifier: Programming Language :: Python :: 3
Classifier: Intended Audience :: Developers
Classifier: Operating System :: OS Independent
License-File: LICENSE
Requires-Dist: requests
Requires-Dist: alive-progress
Requires-Dist: user-agent
Requires-Dist: lxml
Requires-Dist: click
Requires-Dist: prettytable
Requires-Dist: beautifulsoup4
